MANIFEST.in
setup.cfg
setup.py
openmm_transformer/__init__.py
openmm_transformer.egg-info/PKG-INFO
openmm_transformer.egg-info/SOURCES.txt
openmm_transformer.egg-info/dependency_links.txt
openmm_transformer.egg-info/not-zip-safe
openmm_transformer.egg-info/top_level.txt
openmm_transformer/expressions/buckingham_energy
openmm_transformer/transformers/BaseTransformer.py
openmm_transformer/transformers/BuckinghamTransformer.py
openmm_transformer/transformers/__init__.py
openmm_transformer/utilities/__init__.py
openmm_transformer/utilities/prepare_expression.py